LbExec/__init__.py
LbExec/__main__.py
LbExec/cli_utils.py
LbExec/options.py
LbExec/utils.py
LbExec/workflows/__init__.py
LbExec/workflows/mdf_utils.py
LbExec/workflows/process_trees.py
LbExec/workflows/skim_and_merge.py
lbexec-0.9.4.dist-info/licenses/LICENSE
lbexec-0.9.4.dist-info/METADATA
lbexec-0.9.4.dist-info/WHEEL
lbexec-0.9.4.dist-info/entry_points.txt
lbexec-0.9.4.dist-info/top_level.txt
lbexec-0.9.4.dist-info/RECORD
