Metadata-Version: 2.4
Name: LbExec
Version: 0.9.4
Summary: Used for configuring and running LHCb Applications
License: GPL-3.0-only
Project-URL: Homepage, https://gitlab.cern.ch/lhcb-core/LbExec
Classifier: License :: OSI Approved :: GNU General Public License v3 (GPLv3)
Classifier: Programming Language :: Python :: 3
Requires-Python: >=3.11
License-File: LICENSE
Requires-Dist: click>=8.0
Requires-Dist: lbenv
Requires-Dist: pydantic>=2
Requires-Dist: typer-slim>=0.15.0
Requires-Dist: packaging
Requires-Dist: pyyaml>=6.0
Requires-Dist: uproot
Requires-Dist: zstandard
Provides-Extra: testing
Requires-Dist: black; extra == "testing"
Requires-Dist: flake8; extra == "testing"
Requires-Dist: flake8-bugbear; extra == "testing"
Requires-Dist: pylint; extra == "testing"
Requires-Dist: pytest; extra == "testing"
Requires-Dist: pytest-cov; extra == "testing"
Requires-Dist: mypy; extra == "testing"
Requires-Dist: types-PyYAML; extra == "testing"
Requires-Dist: scikit-hep-testdata; extra == "testing"
Dynamic: license-file
